Metadata-Version: 2.1
Name: uecli
Version: 0.0.9
Summary: UEC CLI Tool
Home-page: https://github.com/uec-world-dominators/uecli
Author: shosatojp
Author-email: me@shosato.jp
License: Type license() to see the full license text
Platform: UNKNOWN
Classifier: Programming Language :: Python :: 3
Requires-Python: >=3.6
